adamet/LICENSE.txt
adamet/README.rst
adamet/__init__.py
adamet/adamet.py
adamet/corner_plot.py
adamet/examples/__init__.py
adamet/examples/adamet_example.py
adamet/examples/adamet_reference_output.txt
adamet-2.0.10.dist-info/METADATA
adamet-2.0.10.dist-info/WHEEL
adamet-2.0.10.dist-info/top_level.txt
adamet-2.0.10.dist-info/zip-safe
adamet-2.0.10.dist-info/RECORD
